wizapi/__init__.py
wizapi/wiz.py
wizapi/tests/__init__.py
wizapi/tests/test_ut_wiz.py
wizapi-0.1.1.dist-info/LICENSE.txt
wizapi-0.1.1.dist-info/METADATA
wizapi-0.1.1.dist-info/WHEEL
wizapi-0.1.1.dist-info/top_level.txt
wizapi-0.1.1.dist-info/RECORD
