Metadata-Version: 2.1
Name: wizapi
Version: 0.1.1
Summary: This module provides a Python interface for making API calls to the Wiz.
Author-email: alam <mailtoalam1@gmail.com>
Classifier: Programming Language :: Python :: 3
Classifier: License :: OSI Approved :: MIT License
Classifier: Operating System :: OS Independent
Requires-Python: >=3.9
License-File: LICENSE.txt
Requires-Dist: requests
